{
  "/docs-137": {
    "__comp": "5e95c892",
    "__context": {
      "plugin": "aba21aa0"
    }
  },
  "/docs-def": {
    "__comp": "a7bd4aaa",
    "__props": "0058b4c6"
  },
  "/docs-0f8": {
    "__comp": "a94703ab"
  },
  "/docs/-e35": {
    "__comp": "17896441",
    "content": "23374ca6"
  },
  "/docs/future-enhancements-eae": {
    "__comp": "17896441",
    "content": "8b16887f"
  },
  "/docs/home-e29": {
    "__comp": "17896441",
    "content": "3d9c95a4"
  },
  "/docs/srs/appendices-d49": {
    "__comp": "17896441",
    "content": "3614fc00"
  },
  "/docs/srs/functional-requirements-004": {
    "__comp": "17896441",
    "content": "09afd85b"
  },
  "/docs/srs/interface-requirements-7f2": {
    "__comp": "17896441",
    "content": "cc4b9266"
  },
  "/docs/srs/introduction-2e6": {
    "__comp": "17896441",
    "content": "ecdd95c4"
  },
  "/docs/srs/non-functional-requirements-92b": {
    "__comp": "17896441",
    "content": "65fde98c"
  },
  "/docs/srs/overall-description-327": {
    "__comp": "17896441",
    "content": "a3332f90"
  },
  "/docs/wireframes/components-8fb": {
    "__comp": "17896441",
    "content": "1ab8a20f"
  },
  "/docs/wireframes/overview-5a9": {
    "__comp": "17896441",
    "content": "ad5acffa"
  },
  "/docs/wireframes/screens-6ea": {
    "__comp": "17896441",
    "content": "70ab41d9"
  },
  "/-e5f": {
    "__comp": "1df93b7f",
    "__context": {
      "plugin": "a7456010"
    },
    "config": "5e9f5e1a"
  }
}